{
  "childrenToHide": [],
  "subParts": {
    "Beam Pipe": [
      "BeBeampipe_assembly_0",
      "BeamPipe_assembly_1",
      "SynchRadMask_assembly_2",
      "BeamPipeShield_assembly_3",
      "BeamPipeShield_noRot_assembly_4"
    ],
    "Screen Solenoid": [
      "CompSol_assembly_5",
      "ScreenSol_assembly_6"
    ],
    "LumiCal": [
      "LumiCal_envelope_7",
      "LumiCalInstrumentation_envelope_8",
      "LumiCalCooling_envelope_9",
      "LumiCalBackShield_envelope_10"
    ],
    "Vertex": [
      "Vertex_11"
    ],
    "CDCH": [
      "lvCDCH_12"
    ],
    "Solenoid": [
      "Solenoid_13"
    ],
    "EndPlate Absorber": [
      "EndPlateAbsorber_positive_SimpleCylinder_14",
      "EndPlateAbsorber_negative_SimpleCylinder_15"
    ]
  },
  "maxLevel": 3
}